pvcobrademo/LICENSE
pvcobrademo/cobra_demo_file.py
pvcobrademo/cobra_demo_mic.py
pvcobrademo-3.0.1.dist-info/METADATA
pvcobrademo-3.0.1.dist-info/WHEEL
pvcobrademo-3.0.1.dist-info/entry_points.txt
pvcobrademo-3.0.1.dist-info/top_level.txt
pvcobrademo-3.0.1.dist-info/RECORD
