Metadata-Version: 2.1
Name: pvcobrademo
Version: 3.0.1
Summary: Cobra voice activity detection (VAD) engine demos.
Home-page: https://github.com/Picovoice/cobra
Author: Picovoice
Author-email: hello@picovoice.ai
Keywords: voice activity detection engine,VAD
Classifier: Development Status :: 5 - Production/Stable
Classifier: Intended Audience :: Developers
Classifier: License :: OSI Approved :: Apache Software License
Classifier: Operating System :: OS Independent
Classifier: Programming Language :: Python :: 3
Classifier: Topic :: Multimedia :: Sound/Audio :: Speech
Requires-Python: >=3.9
Requires-Dist: pvcobra==3.0.1
Requires-Dist: pvrecorder==1.2.4
